[
  {
    "id": "p_jor_1",
    "name": "ヤジード・アブ・レイラ",
    "teamId": "JOR",
    "position": "GK",
    "birthDate": "1993-01-28",
    "club": "アル・フセイン",
    "goals": 0,
    "assists": 0,
    "number": 1,
    "shortName": "レイラ"
  },
  {
    "id": "p_jor_15",
    "name": "モハマド・アブ・ハシシュ",
    "teamId": "JOR",
    "position": "MF",
    "birthDate": "1995-05-09",
    "club": "アル・カルマ（イラク）",
    "goals": 0,
    "assists": 0,
    "number": 2,
    "shortName": "ハシシュ"
  },
  {
    "id": "p_jor_9",
    "name": "アブダラー・ナシブ",
    "teamId": "JOR",
    "position": "DF",
    "birthDate": "1994-02-25",
    "club": "アル・ザウラー（イラク）",
    "goals": 0,
    "assists": 0,
    "number": 3,
    "shortName": "ナシブ"
  },
  {
    "id": "p_jor_8",
    "name": "フサム・アブ・ダハブ",
    "teamId": "JOR",
    "position": "DF",
    "birthDate": "2000-05-13",
    "club": "アル・ファイサリー",
    "goals": 0,
    "assists": 0,
    "number": 4,
    "shortName": "ダハブ"
  },
  {
    "id": "p_jor_11",
    "name": "ヤザン・アル・アラブ",
    "teamId": "JOR",
    "position": "DF",
    "birthDate": "1996-01-31",
    "club": "FCソウル（韓国）",
    "goals": 0,
    "assists": 0,
    "number": 5,
    "shortName": "アラブ"
  },
  {
    "id": "p_jor_14",
    "name": "アメル・ジャムース",
    "teamId": "JOR",
    "position": "MF",
    "birthDate": "2002-07-03",
    "club": "アル・ザウラー（イラク）",
    "goals": 0,
    "assists": 0,
    "number": 6,
    "shortName": "ジャムース"
  },
  {
    "id": "p_jor_22",
    "name": "モハマド・アブ・ズライク",
    "teamId": "JOR",
    "position": "FW",
    "birthDate": "1997-12-30",
    "club": "ラジャCA（モロッコ）",
    "goals": 0,
    "assists": 0,
    "number": 7,
    "shortName": "ズライク"
  },
  {
    "id": "p_jor_18",
    "name": "ヌール・アル・ラワブデ",
    "teamId": "JOR",
    "position": "MF",
    "birthDate": "1997-02-24",
    "club": "スランゴール（マレーシア）",
    "goals": 0,
    "assists": 0,
    "number": 8,
    "shortName": "ラワブデ"
  },
  {
    "id": "p_jor_25",
    "name": "アリ・オルワン",
    "teamId": "JOR",
    "position": "FW",
    "birthDate": "2000-03-26",
    "club": "アル・サイリヤ（カタール）",
    "goals": 0,
    "assists": 0,
    "number": 9,
    "shortName": "オルワン"
  },
  {
    "id": "p_jor_20",
    "name": "ムサ・アル・タアマリ",
    "teamId": "JOR",
    "position": "FW",
    "birthDate": "1997-06-10",
    "club": "レンヌ（フランス）",
    "goals": 0,
    "assists": 0,
    "number": 10,
    "shortName": "タアマリ"
  },
  {
    "id": "p_jor_23",
    "name": "オデ・アル・ファフリ",
    "teamId": "JOR",
    "position": "FW",
    "birthDate": "2005-11-22",
    "club": "ピラミッズ（エジプト）",
    "goals": 0,
    "assists": 0,
    "number": 11,
    "shortName": "ファフリ"
  },
  {
    "id": "p_jor_3",
    "name": "ヌール・バニ・アッティアー",
    "teamId": "JOR",
    "position": "GK",
    "birthDate": "1993-01-25",
    "club": "アル・ファイサリー",
    "goals": 0,
    "assists": 0,
    "number": 12,
    "shortName": "アッティアー"
  },
  {
    "id": "p_jor_26",
    "name": "マフムード・アル・マルディ",
    "teamId": "JOR",
    "position": "FW",
    "birthDate": "1993-10-06",
    "club": "アル・フセイン",
    "goals": 0,
    "assists": 0,
    "number": 13,
    "shortName": "マルディ"
  },
  {
    "id": "p_jor_12",
    "name": "ラジャエイ・アエッド",
    "teamId": "JOR",
    "position": "MF",
    "birthDate": "1993-07-25",
    "club": "アル・フセイン",
    "goals": 0,
    "assists": 0,
    "number": 14,
    "shortName": "アエッド"
  },
  {
    "id": "p_jor_16",
    "name": "イブラヒム・サアデ",
    "teamId": "JOR",
    "position": "MF",
    "birthDate": "2000-04-27",
    "club": "アル・カルマ（イラク）",
    "goals": 0,
    "assists": 0,
    "number": 15,
    "shortName": "サアデ"
  },
  {
    "id": "p_jor_10",
    "name": "モハマド・アブ・アル・ナディ",
    "teamId": "JOR",
    "position": "DF",
    "birthDate": "2001-02-08",
    "club": "スランゴール（マレーシア）",
    "goals": 0,
    "assists": 0,
    "number": 16,
    "shortName": "ナディ"
  },
  {
    "id": "p_jor_4",
    "name": "サリム・オバイド",
    "teamId": "JOR",
    "position": "DF",
    "birthDate": "1992-01-17",
    "club": "アル・フセイン",
    "goals": 0,
    "assists": 0,
    "number": 17,
    "shortName": "オバイド"
  },
  {
    "id": "p_jor_21",
    "name": "モハンメド・タハ・アブ・ゴシュ",
    "teamId": "JOR",
    "position": "MF",
    "birthDate": "2005-07-13",
    "club": "アル・フセイン",
    "goals": 0,
    "assists": 0,
    "number": 18,
    "shortName": "ゴシュ"
  },
  {
    "id": "p_jor_5",
    "name": "サエド・アル・ロザン",
    "teamId": "JOR",
    "position": "DF",
    "birthDate": "1997-02-01",
    "club": "アル・フセイン",
    "goals": 0,
    "assists": 0,
    "number": 19,
    "shortName": "ロザン"
  },
  {
    "id": "p_jor_17",
    "name": "モハナド・アブ・タハ",
    "teamId": "JOR",
    "position": "MF",
    "birthDate": "2003-02-02",
    "club": "アル・クワ・アル・ジャウィヤ（イラク）",
    "goals": 0,
    "assists": 0,
    "number": 20,
    "shortName": "タハ"
  },
  {
    "id": "p_jor_19",
    "name": "ニザール・アル・ラシュダン",
    "teamId": "JOR",
    "position": "MF",
    "birthDate": "1999-03-23",
    "club": "カタールSC（カタール）",
    "goals": 0,
    "assists": 0,
    "number": 21,
    "shortName": "ラシュダン"
  },
  {
    "id": "p_jor_2",
    "name": "アブダラー・アル・ファフリ",
    "teamId": "JOR",
    "position": "GK",
    "birthDate": "2000-01-22",
    "club": "アル・ワフダート",
    "goals": 0,
    "assists": 0,
    "number": 22,
    "shortName": "ファフリ"
  },
  {
    "id": "p_jor_6",
    "name": "イフサン・ハダド",
    "teamId": "JOR",
    "position": "DF",
    "birthDate": "1994-02-05",
    "club": "アル・フセイン",
    "goals": 0,
    "assists": 0,
    "number": 23,
    "shortName": "ハダド"
  },
  {
    "id": "p_jor_24",
    "name": "アリ・アザイゼ",
    "teamId": "JOR",
    "position": "FW",
    "birthDate": "2004-04-13",
    "club": "アル・シャバブ（サウジアラビア）",
    "goals": 0,
    "assists": 0,
    "number": 24,
    "shortName": "アザイゼ"
  },
  {
    "id": "p_jor_13",
    "name": "モハマド・アル・ダウード",
    "teamId": "JOR",
    "position": "MF",
    "birthDate": "1992-12-04",
    "club": "アル・ワフダート",
    "goals": 0,
    "assists": 0,
    "number": 25,
    "shortName": "ダウード"
  },
  {
    "id": "p_jor_7",
    "name": "アナス・バダウィ",
    "teamId": "JOR",
    "position": "DF",
    "birthDate": "1997-09-13",
    "club": "アル・ファイサリー",
    "goals": 0,
    "assists": 0,
    "number": 26,
    "shortName": "バダウィ"
  }
]
