[
  { "id": "A", "teamIds": ["MEX", "ZAF", "KOR", "CZE"] },
  { "id": "B", "teamIds": ["CAN", "BIH", "QAT", "SUI"] },
  { "id": "C", "teamIds": ["BRA", "MAR", "HAI", "SCO"] },
  { "id": "D", "teamIds": ["USA", "PAR", "AUS", "TUR"] },
  { "id": "E", "teamIds": ["GER", "CUR", "CIV", "ECU"] },
  { "id": "F", "teamIds": ["NED", "JPN", "SWE", "TUN"] },
  { "id": "G", "teamIds": ["BEL", "EGY", "IRN", "NZL"] },
  { "id": "H", "teamIds": ["ESP", "CPV", "KSA", "URU"] },
  { "id": "I", "teamIds": ["FRA", "SEN", "IRQ", "NOR"] },
  { "id": "J", "teamIds": ["ARG", "ALG", "AUT", "JOR"] },
  { "id": "K", "teamIds": ["POR", "COD", "UZB", "COL"] },
  { "id": "L", "teamIds": ["ENG", "CRO", "GHA", "PAN"] }
]
